verify_domain_cert/__init__.py
verify_domain_cert/check.py
verify_domain_cert-0.1.4.dist-info/METADATA
verify_domain_cert-0.1.4.dist-info/WHEEL
verify_domain_cert-0.1.4.dist-info/entry_points.txt
verify_domain_cert-0.1.4.dist-info/RECORD
